<?xml version="1.0" encoding="UTF8"?>
<messages>
  <message id="Wt.WAbstractItemView.PageIOfN"><b>{1}</b> of <b>{2}</b></message>
  <message id="Wt.WAbstractItemView.PageBar.First">&#x00ab; First</message>
  <message id="Wt.WAbstractItemView.PageBar.Previous">&#x2039; Previous</message>
  <message id="Wt.WAbstractItemView.PageBar.Next">Next &#x203a;</message>
  <message id="Wt.WAbstractItemView.PageBar.Last">Last &#x00bb;</message>
  <message id="Wt.WCalendar.PrevMonth">&#x00ab;</message>
  <message id="Wt.WCalendar.NextMonth">&#x00bb;</message>
  <message id="Wt.WDate.Mon">Mon</message>
  <message id="Wt.WDate.Tue">Tue</message>
  <message id="Wt.WDate.Wed">Wed</message>
  <message id="Wt.WDate.Thu">Thu</message>
  <message id="Wt.WDate.Fri">Fri</message>
  <message id="Wt.WDate.Sat">Sat</message>
  <message id="Wt.WDate.Sun">Sun</message>
  <message id="Wt.WDate.Monday">Monday</message>
  <message id="Wt.WDate.Tuesday">Tuesday</message>
  <message id="Wt.WDate.Wednesday">Wednesday</message>
  <message id="Wt.WDate.Thursday">Thursday</message>
  <message id="Wt.WDate.Friday">Friday</message>
  <message id="Wt.WDate.Saturday">Saturday</message>
  <message id="Wt.WDate.Sunday">Sunday</message>
  <message id="Wt.WDate.Jan">Jan</message>
  <message id="Wt.WDate.Feb">Feb</message>
  <message id="Wt.WDate.Mar">Mar</message>
  <message id="Wt.WDate.Apr">Apr</message>
  <message id="Wt.WDate.May">May</message>
  <message id="Wt.WDate.Jun">Jun</message>
  <message id="Wt.WDate.Jul">Jul</message>
  <message id="Wt.WDate.Aug">Aug</message>
  <message id="Wt.WDate.Sep">Sep</message>
  <message id="Wt.WDate.Oct">Oct</message>
  <message id="Wt.WDate.Nov">Nov</message>
  <message id="Wt.WDate.Dec">Dec</message>
  <message id="Wt.WDate.January">January</message>
  <message id="Wt.WDate.February">February</message>
  <message id="Wt.WDate.March">March</message>
  <message id="Wt.WDate.April">April</message>
  <message id="Wt.WDate.May">May</message>
  <message id="Wt.WDate.June">June</message>
  <message id="Wt.WDate.July">July</message>
  <message id="Wt.WDate.August">August</message>
  <message id="Wt.WDate.September">September</message>
  <message id="Wt.WDate.October">October</message>
  <message id="Wt.WDate.November">November</message>
  <message id="Wt.WDate.December">December</message>
  <message id="Wt.WDatePicker.Close">Close</message>
  <message id="Wt.WDateTime.LessThanASecond">less than a second</message>
  <message id="Wt.WDateTime.second">one second</message>
  <message id="Wt.WDateTime.seconds">{1} seconds</message>
  <message id="Wt.WDateTime.minute">one minute</message>
  <message id="Wt.WDateTime.minutes">{1} minutes</message>
  <message id="Wt.WDateTime.hour">one hour</message>
  <message id="Wt.WDateTime.hours">{1} hours</message>
  <message id="Wt.WDateTime.day">one day</message>
  <message id="Wt.WDateTime.days">{1} days</message>
  <message id="Wt.WDateTime.week">one week</message>
  <message id="Wt.WDateTime.weeks">{1} weeks</message>
  <message id="Wt.WDateTime.month">one month</message>
  <message id="Wt.WDateTime.months">{1} months</message>
  <message id="Wt.WDateTime.year">one year</message>
  <message id="Wt.WDateTime.years">{1} years</message>
  <message id="Wt.WDateTime.null">Null</message>
  <message id="Wt.WDateValidator.DateTooEarly">The date must be after {1}</message>
  <message id="Wt.WDateValidator.DateTooLate">The date must be before {1}</message>
  <message id="Wt.WDateValidator.WrongDateRange">The date must be between {1} and {2}</message>
  <message id="Wt.WDateValidator.WrongFormat">Must be a date in the format '{1}'</message>
  <message id="Wt.WDefaultLoadingIndicator.Loading">Loading...</message>
  <message id="Wt.WDoubleValidator.NotANumber">Must be a number</message>
  <message id="Wt.WDoubleValidator.TooSmall">The number must be larger than {1}</message>
  <message id="Wt.WDoubleValidator.BadRange">The number must be in the range {1} to {2}</message>
  <message id="Wt.WDoubleValidator.TooLarge">The number must be smaller than {1}</message>
  <message id="Wt.WInPlaceEdit.Save">Save</message>
  <message id="Wt.WInPlaceEdit.Cancel">Cancel</message>
  <message id="Wt.WIntValidator.NotAnInteger">Must be an integer number</message>
  <message id="Wt.WIntValidator.TooSmall">The number must be larger than {1}</message>
  <message id="Wt.WIntValidator.BadRange">The number must be in the range {1} to {2}</message>
  <message id="Wt.WIntValidator.TooLarge">The number must be smaller than {1}</message>
  <message id="Wt.WLengthValidator.TooShort">The input must be at least {1} characters</message>
  <message id="Wt.WLengthValidator.BadRange">The input must have a length between {1} and {2} characters</message>
  <message id="Wt.WLengthValidator.TooLong">The input must be no more than {1} characters</message>
  <message id="Wt.WMessageBox.Abort">Abort</message>
  <message id="Wt.WMessageBox.Cancel">Cancel</message>
  <message id="Wt.WMessageBox.Ignore">Ignore</message>
  <message id="Wt.WMessageBox.No">No</message>
  <message id="Wt.WMessageBox.NoToAll">No to All</message>
  <message id="Wt.WMessageBox.Ok">Ok</message>
  <message id="Wt.WMessageBox.Retry">Retry</message>
  <message id="Wt.WMessageBox.Yes">Yes</message>
  <message id="Wt.WMessageBox.YesToAll">Yes to All</message>
  <message id="Wt.WOverlayLoadingIndicator.Loading">Loading...</message>
  <message id="Wt.WRegExpValidator.Invalid">Invalid input</message>
  <message id="Wt.WValidator.Invalid">This field cannot be empty</message>
</messages>
